Metadata-Version: 2.1
Name: cytoolz-stubs
Version: 0.0.1
Summary: PEP 561 type stubs for cytoolz
Home-page: https://github.com/blindspot-ai/cytoolz-stubs
Maintainer: Martin Matyasek
Maintainer-email: martin.matyasek@blindspot.ai
License: MIT
Keywords: cytoolz stubs
Platform: UNKNOWN
Classifier: Development Status :: 4 - Beta
Classifier: Environment :: Console
Classifier: Intended Audience :: Developers
Classifier: Natural Language :: English
Classifier: Operating System :: Unix
Classifier: Programming Language :: Python
Classifier: Programming Language :: Python :: 3
Classifier: Programming Language :: Python :: 3.6
Classifier: Programming Language :: Python :: 3.7
Requires-Python: >=3.6
Provides-Extra: dev
Provides-Extra: test
